AUTHORS
HISTORY
LICENSE
MANIFEST.in
README.md
setup.cfg
setup.py
tests/__init__.py
wikidict/__init__.py
wikidict/lancodes.py
wikidict/wikidict.py
wikidict.egg-info/PKG-INFO
wikidict.egg-info/SOURCES.txt
wikidict.egg-info/dependency_links.txt
wikidict.egg-info/entry_points.txt
wikidict.egg-info/not-zip-safe
wikidict.egg-info/top_level.txt