Metadata-Version: 1.1
Name: wikidict
Version: 1.2.0
Summary: Wikipedia at your fingertips
Home-page: https://github.com/walidsa3d/wikidict
Author: Walid Saad
Author-email: walid.sa3d@gmail.com
License: mit
Platform: UNKNOWN
Classifier: Development Status :: 4 - Beta
Classifier: Environment :: Console
Classifier: Intended Audience :: End Users/Desktop
Classifier: Operating System :: OS Independent
Classifier: Natural Language :: English
Classifier: Programming Language :: Python :: 2
Classifier: Topic :: Utilities
